{
  "title": "Eurasian Century News",
  "url": "https://example.com/",
  "description": "China, Russia & Iran are building the post-Atlantic world order regardless of supranational Trans-Atlantic elites.",
  "feed": {
    "subtitle": "Unveiling the imperialist + unholy war animating US domestic + foreign policy, predatory capitalism, corruption, MSM propaganda + Anglo-American banking mafia.",
    "filename": "feed.xml",
    "path": "/feed/feed.xml",
    "id": "https://example.com/"
  },
  "jsonfeed": {
    "path": "/feed/feed.json",
    "url": "https://example.com/feed/feed.json"
  },
  "author": {
    "name": "Your Name Here",
    "email": "youremailaddress@example.com",
    "url": "https://example.com/about-me/"
  }
}
